odoo/addons/mrp_restrict_lot/README.rst
odoo/addons/mrp_restrict_lot/__init__.py
odoo/addons/mrp_restrict_lot/__manifest__.py
odoo/addons/mrp_restrict_lot/i18n/es.po
odoo/addons/mrp_restrict_lot/i18n/it.po
odoo/addons/mrp_restrict_lot/i18n/mrp_restrict_lot.pot
odoo/addons/mrp_restrict_lot/models/__init__.py
odoo/addons/mrp_restrict_lot/models/mrp_production.py
odoo/addons/mrp_restrict_lot/models/stock_rule.py
odoo/addons/mrp_restrict_lot/readme/CONTRIBUTORS.md
odoo/addons/mrp_restrict_lot/readme/DESCRIPTION.md
odoo/addons/mrp_restrict_lot/readme/USAGE.md
odoo/addons/mrp_restrict_lot/static/description/icon.png
odoo/addons/mrp_restrict_lot/static/description/index.html
odoo/addons/mrp_restrict_lot/tests/__init__.py
odoo/addons/mrp_restrict_lot/tests/test_manufaturing_lot.py
odoo_addon_mrp_restrict_lot-18.0.1.0.3.dist-info/METADATA
odoo_addon_mrp_restrict_lot-18.0.1.0.3.dist-info/WHEEL
odoo_addon_mrp_restrict_lot-18.0.1.0.3.dist-info/top_level.txt
odoo_addon_mrp_restrict_lot-18.0.1.0.3.dist-info/RECORD
