Metadata-Version: 2.1
Name: odoo-addon-mrp_restrict_lot
Version: 18.0.1.0.3
Requires-Python: >=3.10
Requires-Dist: odoo-addon-stock_restrict_lot==18.0.*
Requires-Dist: odoo==18.0.*
Summary: MRP Restrict Lot
Home-page: https://github.com/OCA/manufacture
License: AGPL-3
Author: Akretion,Odoo Community Association (OCA)
Author-email: support@odoo-community.org
Classifier: Programming Language :: Python
Classifier: Framework :: Odoo
Classifier: Framework :: Odoo :: 18.0
Classifier: License :: OSI Approved :: GNU Affero General Public License v3
Classifier: Development Status :: 4 - Beta
